predictnow/__init__.py
predictnow/find_files_with_specific_extensions.py
predictnow/notifier.py
predictnow/pdapi.py
predictnow/predict_result.py
predictnow/training_result.py
predictnow_api_client-0.0.5.dist-info/LICENSE.txt
predictnow_api_client-0.0.5.dist-info/METADATA
predictnow_api_client-0.0.5.dist-info/WHEEL
predictnow_api_client-0.0.5.dist-info/top_level.txt
predictnow_api_client-0.0.5.dist-info/RECORD
