Metadata-Version: 2.1
Name: predictnow-api-client
Version: 0.0.5
Summary: A restful client library, designed to access predictnow restful api.
Home-page: https://github.com/predictnow/predictnow-mono
Author: PredictNow SDK Dev
Author-email: rikky.hermanto@gmail.com
License: UNKNOWN
Platform: UNKNOWN
Classifier: Programming Language :: Python :: 3
Classifier: Operating System :: OS Independent
Requires-Python: >=3.7
Requires-Dist: pandas (==1.1.4)
Requires-Dist: firebase-admin (==4.4.0)
Requires-Dist: pyarrow (==2.0.0)
